crypto_candle_fetcher/__init__.py
crypto_candle_fetcher/crypto_candle_fetcher.py
crypto_candle_fetcher/data_processing.py
crypto_candle_fetcher/data/.gitkeep
crypto_candle_fetcher/data/Example.csv
crypto_candle_fetcher/data/binance_btcusdt_1d.csv
crypto_candle_fetcher/exchanges/binance.py
crypto_candle_fetcher/exchanges/bingx.py
crypto_candle_fetcher/exchanges/bitstamp.py
crypto_candle_fetcher/exchanges/bybit.py
crypto_candle_fetcher/exchanges/coinbase.py
crypto_candle_fetcher/exchanges/cryptocom.py
crypto_candle_fetcher/exchanges/gateio.py
crypto_candle_fetcher/exchanges/huobi.py
crypto_candle_fetcher/exchanges/kraken.py
crypto_candle_fetcher/exchanges/kucoin.py
crypto_candle_fetcher/exchanges/mexc.py
crypto_candle_fetcher/exchanges/okx.py
crypto_candle_fetcher-0.1.6.dist-info/LICENSE
crypto_candle_fetcher-0.1.6.dist-info/METADATA
crypto_candle_fetcher-0.1.6.dist-info/WHEEL
crypto_candle_fetcher-0.1.6.dist-info/top_level.txt
crypto_candle_fetcher-0.1.6.dist-info/RECORD
