Metadata-Version: 2.2
Name: crypto-candle-fetcher
Version: 0.1.6
Summary: A Python library for fetching OHLC data from multiple cryptocurrency exchanges.
Home-page: https://github.com/metupia/crypto-candle-fetcher
Author: Metupia
Author-email: metupia.git@gmail.com
Classifier: Programming Language :: Python :: 3
Classifier: License :: OSI Approved :: MIT License
Classifier: Operating System :: OS Independent
Requires-Python: >=3.7
License-File: LICENSE
Requires-Dist: requests
Requires-Dist: pandas
Dynamic: author
Dynamic: author-email
Dynamic: classifier
Dynamic: description
Dynamic: description-content-type
Dynamic: home-page
Dynamic: requires-dist
Dynamic: requires-python
Dynamic: summary
